nanohub/__init__.py
nanohub/_version.py
nanohub/remote/__init__.py
nanohub/uidl/__init__.py
nanohub-0.1.0.dist-info/METADATA
nanohub-0.1.0.dist-info/WHEEL
nanohub-0.1.0.dist-info/top_level.txt
nanohub-0.1.0.dist-info/RECORD
