Metadata-Version: 2.1
Name: nanohub
Version: 0.1.0
Summary: A set of tools to run nanohub web apis
Home-page: https://github.com/denphi/nanohub
Author: nanoHUB contributor
Author-email: denphi@denphi.com
License: BSD
Keywords: IPython
Platform: Linux
Platform: Mac OS X
Platform: Windows
Classifier: Intended Audience :: Developers
Classifier: Intended Audience :: Science/Research
Classifier: License :: OSI Approved :: BSD License
Classifier: Programming Language :: Python
Classifier: Programming Language :: Python :: 3
Classifier: Programming Language :: Python :: 3.4
Classifier: Programming Language :: Python :: 3.5
Classifier: Programming Language :: Python :: 3.6
Classifier: Framework :: Jupyter
Requires-Dist: nanohub.remote (>=0.1.0)
Requires-Dist: nanohub.uidl (>=0.1.0)
Provides-Extra: docs
Provides-Extra: examples
Provides-Extra: test
